fpga/tproject/counter.v
module counter(out, clk, reset);
  parameter WIDTH = 8;

  output [WIDTH - 1 : 0] out;
  input 	       clk, reset;

  reg [WIDTH - 1 : 0]   out;
  wire 	       clk, reset;

  always @(posedge clk or posedge reset)
    if (reset)
      out <= 0;
    else
      out <= out + 1;

endmodule // counter

fpga/tproject/counter_tb.v
module test;
/* Make a reset that pulses once. */
  reg reset = 0;
  initial begin
     $dumpfile("io_signals.vcd");
     $dumpvars(0, c1);
     # 17 reset = 1;
     # 11 reset = 0;
     # 29 reset = 1;
     # 11 reset = 0;
     # 100 $finish;
  end
/* Make a regular pulsing clock. */
  reg clk = 0;
  always #5 clk = !clk;
  wire [7:0] value;
  counter c1 (value, clk, reset);
initial
     $monitor("At time %t, value = %h (%0d)",
              $time, value, value);
endmodule // test

fpga/tproject/io_signals.vcd
$date
	Mon Mar 29 23:26:48 2021
$end
$version
	Icarus Verilog
$end
$timescale
	1s
$end
$scope module test $end
$scope module c1 $end
$var wire 1 ! clk $end
$var wire 1 " reset $end
$var reg 8 # out [7:0] $end
$upscope $end
$upscope $end
$enddefinitions $end
#0
$dumpvars
bx #
0"
0!
$end
#5
1!
#10
0!
#15
1!
#17
b0 #
1"
#20
0!
#25
1!
#28
0"
#30
0!
#35
b1 #
1!
#40
0!
#45
b10 #
1!
#50
0!
#55
b11 #
1!
#57
b0 #
1"
#60
0!
#65
1!
#68
0"
#70
0!
#75
b1 #
1!
#80
0!
#85
b10 #
1!
#90
0!
#95
b11 #
1!
#100
0!
#105
b100 #
1!
#110
0!
#115
b101 #
1!
#120
0!
#125
b110 #
1!
#130
0!
#135
b111 #
1!
#140
0!
#145
b1000 #
1!
#150
0!
#155
b1001 #
1!
#160
0!
#165
b1010 #
1!
